setup.py
udc_distr_jvb/Binomialdistribution.py
udc_distr_jvb/Gaussiandistribution.py
udc_distr_jvb/Generaldistribution.py
udc_distr_jvb/__init__.py
udc_distr_jvb.egg-info/PKG-INFO
udc_distr_jvb.egg-info/SOURCES.txt
udc_distr_jvb.egg-info/dependency_links.txt
udc_distr_jvb.egg-info/not-zip-safe
udc_distr_jvb.egg-info/top_level.txt