Metadata-Version: 1.0
Name: udc-distr-jvb
Version: 0.1
Summary: Gaussian distributions and Binomial distributions
Home-page: UNKNOWN
Author: Jorge Villarroel
Author-email: UNKNOWN
License: UNKNOWN
Platform: UNKNOWN
